settingsd/pathing.py
settingsd/base.py
settingsd/loaders.py
settingsd/finders.py
settingsd/utils.py
settingsd/api.py
settingsd/defaults.py
settingsd/__init__.py
settingsd/extras/base.py
settingsd/extras/django.py
settingsd/extras/__init__.py
settingsd-0.8.13.dist-info/WHEEL
settingsd-0.8.13.dist-info/metadata.json
settingsd-0.8.13.dist-info/RECORD
settingsd-0.8.13.dist-info/top_level.txt
settingsd-0.8.13.dist-info/METADATA
settingsd-0.8.13.dist-info/DESCRIPTION.rst
settingsd-0.8.13.dist-info/zip-safe
