Metadata-Version: 2.0
Name: settingsd
Version: 0.8.13
Summary: settings.d
Home-page: https://github.com/xtfxme/settingsd
Author: C Anthony Risinger
Author-email: c@anthonyrisinger.com
License: BSD
Platform: UNKNOWN
Classifier: Development Status :: 4 - Beta
Classifier: License :: OSI Approved :: BSD License
Classifier: Programming Language :: Python
Classifier: Intended Audience :: Developers
